<?xml version="1.0"?>

<consonants>
<c id="1">
m
</c>
<c id="2">
'
</c>
<c id="3">
n
</c>
<c id="4">
h
</c>
<c id="5">
p
</c>
<c id="6">
ch
</c>
<c id="7">
l
</c>
<c id="8">
v
</c>
<c id="9">
th
</c>
<c id="10">
g
</c>
<c id="11">
k
</c>
<c id="12">
kh
</c>
<c id="13">
f
</c>
<c id="14">
r
</c>
<c id="15">
q
</c>
<c id="16">
z
</c>
<c id="17">
j
</c>
<c id="18">
b
</c>
<c id="19">
t
</c>
<c id="20">
sh
</c>
<c id="21">
y
</c>
<c id="22">
d
</c>
<c id="23">
s
</c>
<c id="24">
dh
</c>
<c id="25">
w
</c>
<c id="26">
@
</c>
<c id="27">
ng
</c>
</consonants>
